README
setup.py
texwat/__init__.py
texwat.egg-info/PKG-INFO
texwat.egg-info/SOURCES.txt
texwat.egg-info/dependency_links.txt
texwat.egg-info/not-zip-safe
texwat.egg-info/requires.txt
texwat.egg-info/top_level.txt