Metadata-Version: 1.2
Name: texwat
Version: 0.0
Summary: Convert Python objects to corresponding Latex source code.
Home-page: https://gitlab.com/Dominik1123/Texwat
Author: Dominik Vilsmeier
Author-email: dominik.vilsmeier1123@gmail.com
License: BSD-3-Clause
Keywords: Latex tex converter utility
Platform: UNKNOWN
Classifier: Development Status :: 1 - Planning
Classifier: License :: OSI Approved :: BSD License
Classifier: Programming Language :: Python :: 3.5
Classifier: Programming Language :: Python :: 3.6
Classifier: Topic :: Documentation
Classifier: Topic :: Utilities
Requires-Python: >=3.5
